imglyb/OSXAWTwrapper.py
imglyb/__init__.py
imglyb/accesses.py
imglyb/caches.py
imglyb/config.py
imglyb/imglib_ndarray.py
imglyb/ndarray_like_as_img.py
imglyb/reference_store.py
imglyb/types.py
imglyb/util.py
imglyb-2.1.0.dist-info/LICENSE.txt
imglyb-2.1.0.dist-info/METADATA
imglyb-2.1.0.dist-info/WHEEL
imglyb-2.1.0.dist-info/top_level.txt
imglyb-2.1.0.dist-info/RECORD
