Metadata-Version: 2.1
Name: imglyb
Version: 2.1.0
Summary: A python module to bring together the worlds of NumPy (Python) and ImgLib2 (Java).
Author: Philipp Hanslovsky, Edward Evans, Mark Hiner, Gabriel Selzer
Author-email: Curtis Rueden <ctrueden@wisc.edu>
License: Simplified BSD License
Project-URL: homepage, https://github.com/imglib/imglyb
Project-URL: documentation, https://github.com/imglib/imglyb/blob/main/README.md
Project-URL: source, https://github.com/imglib/imglyb
Project-URL: download, https://pypi.org/project/imglyb/
Project-URL: tracker, https://github.com/imglib/imglyb/issues
Keywords: java,maven,cross-language,numpy,imglib2
Classifier: Development Status :: 5 - Production/Stable
Classifier: Intended Audience :: Developers
Classifier: Intended Audience :: Education
Classifier: Intended Audience :: Science/Research
Classifier: Programming Language :: Python :: 3 :: Only
Classifier: Programming Language :: Python :: 3.7
Classifier: Programming Language :: Python :: 3.8
Classifier: Programming Language :: Python :: 3.9
Classifier: Programming Language :: Python :: 3.10
Classifier: License :: OSI Approved :: BSD License
Classifier: Operating System :: Microsoft :: Windows
Classifier: Operating System :: Unix
Classifier: Operating System :: MacOS
Classifier: Topic :: Scientific/Engineering
Classifier: Topic :: Scientific/Engineering :: Image Processing
Classifier: Topic :: Scientific/Engineering :: Visualization
Classifier: Topic :: Software Development :: Libraries :: Java Libraries
Classifier: Topic :: Software Development :: Libraries :: Python Modules
Classifier: Topic :: Utilities
Requires-Python: >=3.7
Provides-Extra: dev
License-File: LICENSE.txt
